pytatsu_tui/__init__.py
pytatsu_tui/__main__.py
pytatsu_tui/api.py
pytatsu_tui/bins/Darwin/img4tool
pytatsu_tui/bins/Linux/img4tool
pytatsu_tui/bins/Windows/img4tool
pytatsu_tui/config.py
pytatsu_tui/devices.py
pytatsu_tui/jungle.py
pytatsu_tui/parse.py
pytatsu_tui-0.2.6.dist-info/METADATA
pytatsu_tui-0.2.6.dist-info/WHEEL
pytatsu_tui-0.2.6.dist-info/entry_points.txt
pytatsu_tui-0.2.6.dist-info/RECORD
