Metadata-Version: 2.1
Name: pytatsu-tui
Version: 0.2.6
Summary: A way to save/manage *OS blobs using pytatsu
Home-page: https://github.com/doms9/pytatsu-tui
License: LGPL-3.0-only
Author: doms9
Author-email: domsenueve@gmail.com
Requires-Python: >=3.10,<4.0
Classifier: License :: OSI Approved :: GNU Lesser General Public License v3 (LGPLv3)
Classifier: Programming Language :: Python :: 3
Classifier: Programming Language :: Python :: 3.10
Classifier: Programming Language :: Python :: 3.11
Requires-Dist: attrs (>=22.2.0,<23.0.0)
Requires-Dist: colorama (>=0.4.6,<0.5.0)
Requires-Dist: httpx (>=0.23.3,<0.24.0)
Requires-Dist: nest-asyncio (>=1.5.6,<2.0.0)
Requires-Dist: pyimg4 (>=0.7,<0.8)
Requires-Dist: pytatsu (>=0.1.5,<0.2.0)
Requires-Dist: remotezip (>=0.9.4,<0.10.0)
Requires-Dist: send2trash (>=1.8.0,<2.0.0)
Requires-Dist: termcolor (>=2.2.0,<3.0.0)
Project-URL: Bug Tracker, https://github.com/doms9/pytatsu-tui/issues
Project-URL: Repository, https://github.com/doms9/pytatsu-tui
